winreglib.py
winreglib-0.2.0.dist-info/METADATA
winreglib-0.2.0.dist-info/WHEEL
winreglib-0.2.0.dist-info/top_level.txt
winreglib-0.2.0.dist-info/RECORD
