Metadata-Version: 2.1
Name: winreglib
Version: 0.2.0
Summary: High level, class based Windows registry manipulation
Home-page: https://github.com/adamkerz/winreglib
Author: Adam Kerz
Author-email: github@kerz.id.au
License: BSD 3-Clause
Keywords: winreg
Classifier: Development Status :: 4 - Beta
Classifier: Intended Audience :: Developers
Classifier: Natural Language :: English
Classifier: Operating System :: Microsoft :: Windows
Classifier: Programming Language :: Python
Classifier: Programming Language :: Python :: 3
Classifier: Programming Language :: Python :: 3.6
Classifier: Programming Language :: Python :: 3.7
Classifier: Programming Language :: Python :: 3.8
Classifier: Programming Language :: Python :: 3.9
Classifier: Programming Language :: Python :: 3.10
Classifier: Topic :: Software Development :: Libraries :: Python Modules
